{
  "map_code": "6593_4576_5192",
  "map_name": "BASE WARS SLIDE CHILL \ud83c\udf1f HEROES",
  "collection_date": "2026-02-25",
  "collection_timestamp": "2026-02-25T06:56:35.084683",
  "data_range": {
    "from": "2025-11-14T00:00:00.000Z",
    "to": "2025-11-20T23:11:00.000Z"
  },
  "ccu_readings": [
    113,
    116,
    110,
    104,
    101,
    100,
    97,
    86,
    85,
    83,
    75,
    47,
    52,
    56,
    46,
    46,
    54,
    55,
    46,
    56,
    45,
    51,
    56,
    57,
    64,
    62,
    65,
    66,
    70,
    76,
    83,
    88,
    101,
    115,
    120,
    106,
    136,
    127,
    140,
    136,
    131,
    122,
    132,
    136,
    131,
    135,
    131,
    131,
    130,
    115,
    113,
    113,
    111,
    100,
    106,
    112,
    110,
    86,
    88,
    92,
    89,
    72,
    62,
    59,
    57,
    54,
    56,
    62,
    65,
    69,
    78,
    77,
    77,
    87,
    85,
    104,
    112,
    126,
    121,
    129,
    120,
    128,
    138,
    154,
    150,
    139,
    139,
    131,
    124,
    133,
    119,
    119,
    124,
    136,
    110,
    113,
    119,
    128,
    110,
    114,
    128,
    121,
    122,
    113,
    97,
    89,
    81,
    84,
    64,
    65,
    63,
    58,
    58,
    55,
    66,
    69,
    85,
    74,
    88,
    88,
    94,
    101,
    91,
    89,
    102,
    110,
    128,
    130,
    0,
    127,
    150,
    136,
    153,
    163,
    157,
    158,
    163,
    132,
    137,
    139,
    133,
    136,
    114,
    108,
    110,
    103,
    97,
    86,
    96,
    93,
    87,
    93,
    93,
    66,
    60,
    54,
    41,
    34,
    34,
    33,
    27,
    31,
    38,
    43,
    46,
    41,
    47,
    51,
    50,
    46,
    59,
    77,
    79,
    75,
    82,
    93,
    78,
    84,
    88,
    104,
    112,
    103,
    94,
    101,
    104,
    109,
    101,
    105,
    109,
    104,
    94,
    91,
    78,
    88,
    100,
    101,
    95,
    83,
    85,
    91,
    82,
    78,
    60,
    70,
    56,
    45,
    41,
    41,
    39,
    32,
    37,
    34,
    34,
    42,
    44,
    48,
    51,
    49,
    64,
    61,
    64,
    78,
    85,
    84,
    95,
    105,
    106,
    108,
    111,
    109,
    107,
    103,
    106,
    107,
    113,
    119,
    107,
    95,
    98,
    82,
    87,
    92,
    94,
    92,
    83,
    92,
    84,
    83,
    82,
    57,
    59,
    56,
    56,
    44,
    41,
    43,
    35,
    37,
    19,
    0,
    0,
    8,
    23,
    31,
    43,
    45,
    44,
    43,
    56,
    54,
    66,
    65,
    60,
    72,
    78,
    100,
    108,
    106,
    104,
    108,
    106,
    95,
    99,
    86,
    88,
    96,
    104,
    107,
    104,
    106,
    116,
    103,
    108,
    86,
    86,
    87,
    64,
    67,
    60,
    60,
    50,
    47,
    44,
    39,
    40,
    36,
    33,
    34,
    33,
    44,
    46,
    42,
    44,
    51,
    62,
    67,
    77,
    90,
    93,
    109,
    110,
    130,
    135,
    130,
    137,
    115,
    125,
    127,
    124,
    108,
    99,
    103,
    106,
    125,
    114
  ],
  "num_readings": 335,
  "summary": {
    "avg_ccu": 86.36,
    "max_ccu": 163,
    "min_ccu": 0,
    "std_ccu": 33.03,
    "median_ccu": 88.0
  },
  "trend_features": {
    "trend_slope": -0.0723,
    "recent_momentum": -5.85,
    "volatility": 33.03
  },
  "map_metadata": {
    "creator_followers": 0,
    "in_discovery": 0,
    "xp_enabled": 0,
    "num_tags": 4,
    "tags": [
      "2v2",
      "3v3",
      "free for all",
      "battle"
    ],
    "max_players": 0,
    "version": 20,
    "created_at": "",
    "type": "uefn",
    "image_url": ""
  },
  "creator": {
    "name": "Sorus.",
    "code": "",
    "followers": 0
  }
}