{
  "map_code": "0997-1163-8933",
  "map_data": {
    "attributions": [],
    "ccu_record": 1926,
    "ccu_record_date": "2025-02-01T20:00:00.000Z",
    "created": "2025-10-10T14:07:50.844Z",
    "discovery_intent": "PUBLIC",
    "id": "0997-1163-8933",
    "image_url": "https://cdn-0001.qstv.on.epicgames.com/svZriXjYAdyWUzzpSW/image/landscape_comp.jpeg",
    "image_url_cohort_b": null,
    "introduction": "\ud83d\udcbe Ranks and Eliminations Save\n\ud83c\udfc6 Custom Leaderboard Featured\n\ud83d\udd2b Choose Your Favorite Weapons",
    "lastSyncCcu": 97,
    "lastSyncDate": "2025-11-20T21:29:00.000Z",
    "lastSyncDisabled": false,
    "lobby_background_image_url": "https://cdn-0001.qstv.on.epicgames.com/VonZYFwddiOGcZQsFo/image/lobby.jpeg",
    "locale": "ar",
    "max_players": 16,
    "metrics_day_id": 455,
    "metrics_minute_id": 477,
    "metrics_updated_date": "2025-11-20T19:45:30.623Z",
    "minutes_played": 242030424,
    "minutes_played_sync_date": "2025-11-14T22:39:22.102Z",
    "moderation_status": "Approved",
    "name": "\u062f\u0648 \u0633\u0643\u0631\u0645\u0632 \u0627\u0644\u0645\u0639\u0631\u0642\u064a\u0646 \ud83c\udfc6 DUO SCRIMS RANKED",
    "owner_code": "gx2",
    "owner_name": "TheRealGX2",
    "published": "2024-12-03T14:55:27.673Z",
    "ratings": [
      "ACB_AGE_M",
      "PEGI_AGE_12",
      "GEN_AGE_12",
      "CLASSIND_AGE_12",
      "USK_AGE_12",
      "GRAC_AGE_ALL",
      "ESRB_AGE_T",
      "RUSSIA_AGE_16"
    ],
    "square_image_url": "https://cdn-0001.qstv.on.epicgames.com/xFOlceFcwyTNVXjZdP/image/square.jpeg",
    "state": "in_discovery",
    "tagline": "\ud83d\ude09 Welcome to Scrims! Compete with team players to sharpen your skills or just have fun\n\ud83c\udf00 ZONE WARS\n\ud83c\udfc6 16-Player 2V2 Zonewars\n\ud83d\udd2b Choose your favorite weapons\n\ud83c\udf81 Spin the wheel of fortune\n\u270f\ufe0f Improve your builds\n\ud83d\udcdd Practice and train\n\ud83c\udfaf Custom ranking system\n\u2b50 Name tags ON\n\ud83e\udd29 Endless fun and items\n\ud83d\udcaa Train your aim\n\ud83c\udfc3 Fast-paced action\n\ud83d\udea8 Become the best player in teams among 16 players\nFrequent updates with new content \ud83c\udd95\n\ud83d\udcbeSaved eliminations data and leaderboard\n\ud83d\udee0Created in UEFN / Creative 2.0",
    "tags": [
      "zonewars",
      "2v2",
      "practice",
      "duo"
    ],
    "type": "uefn",
    "version": 113,
    "xp_enabled": true,
    "creator": {
      "id": "gx2",
      "last_sync_ccu": 1469,
      "last_sync_minutes_played": 1398669384,
      "last_sync_minutes_played_position": 42,
      "last_sync_position": 46,
      "lookup_avatar": "https://cdn-0001.qstv.on.epicgames.com/06QzvkAQMDEY4OF0UoRy9E/image.jpg",
      "lookup_banner": "https://cdn-0001.qstv.on.epicgames.com/066rrHHyhnBdIKbot9BHEy/image.jpg",
      "lookup_bio": "Follow me on my socials to stay up to date with all my games!",
      "lookup_display_name": "gx2",
      "lookup_follower_count": 162864,
      "lookup_socials_discord": "gAjpaX9FaH",
      "lookup_socials_instagram": "gamer_x.gx2",
      "lookup_socials_youtube": "@Hammoda",
      "name": "TheRealGX2"
    }
  },
  "stats_24h": {
    "success": true,
    "data": {
      "from": "2025-11-19T22:08:00.000Z",
      "to": "2025-11-20T22:06:00.000Z",
      "stats": [
        82,
        81,
        78,
        79,
        79,
        80,
        78,
        78,
        76,
        76,
        75,
        75,
        66,
        66,
        65,
        71,
        64,
        65,
        65,
        69,
        64,
        62,
        63,
        60,
        60,
        60,
        63,
        62,
        70,
        75,
        61,
        59,
        70,
        70,
        73,
        71,
        71,
        69,
        69,
        72,
        70,
        75,
        75,
        70,
        70,
        69,
        69,
        70,
        66,
        65,
        61,
        68,
        63,
        66,
        66,
        74,
        72,
        71,
        73,
        70,
        70,
        71,
        67,
        64,
        66,
        66,
        66,
        66,
        61,
        61,
        63,
        59,
        72,
        67,
        67,
        72,
        74,
        78,
        78,
        79,
        79,
        74,
        66,
        72,
        72,
        71,
        74,
        74,
        75,
        76,
        76,
        85,
        85,
        82,
        85,
        82,
        82,
        80,
        80,
        87,
        88,
        90,
        87,
        87,
        99,
        94,
        84,
        91,
        91,
        92,
        92,
        88,
        85,
        85,
        82,
        82,
        91,
        91,
        81,
        81,
        77,
        80,
        69,
        69,
        69,
        66,
        73,
        70,
        88,
        88,
        81,
        86,
        72,
        72,
        77,
        80,
        80,
        79,
        88,
        98,
        99,
        99,
        97,
        97,
        90,
        91,
        100,
        109,
        108,
        108,
        108,
        114,
        109,
        109,
        104,
        104,
        97,
        97,
        99,
        99,
        98,
        93,
        102,
        102,
        98,
        98,
        97,
        84,
        87,
        85,
        85,
        89,
        94,
        94,
        92,
        90,
        87,
        87,
        98,
        91,
        91,
        92,
        86,
        86,
        101,
        101,
        98,
        107,
        88,
        93,
        91,
        99,
        87,
        87,
        98,
        93,
        93,
        94,
        96,
        97,
        82,
        87,
        87,
        87,
        87,
        96,
        90,
        88,
        104,
        104,
        100,
        100,
        97,
        97,
        97,
        111,
        111,
        102,
        102,
        103,
        103,
        95,
        96,
        96,
        98,
        86,
        85,
        85,
        82,
        86,
        93,
        91,
        91,
        91,
        91,
        95,
        94,
        92,
        85,
        85,
        85,
        87,
        92,
        92,
        89,
        79,
        84,
        81,
        81,
        71,
        69,
        69,
        61,
        61,
        65,
        62,
        62,
        60,
        62,
        62,
        62,
        61,
        73,
        71,
        78,
        68,
        73,
        67,
        68,
        67,
        61,
        61,
        69,
        69,
        56,
        62,
        56,
        56,
        56,
        54,
        54,
        55,
        54,
        54,
        63,
        67,
        63,
        63,
        70,
        63,
        63,
        66,
        63,
        63,
        55,
        61,
        63,
        60,
        52,
        59,
        56,
        50,
        44,
        36,
        34,
        33,
        39,
        37,
        37,
        37,
        36,
        36,
        36,
        36,
        38,
        39,
        35,
        36,
        34,
        32,
        32,
        32,
        27,
        30,
        31,
        30,
        34,
        34,
        33,
        26,
        26,
        34,
        27,
        30,
        26,
        30,
        30,
        34,
        33,
        34,
        38,
        38,
        33,
        30,
        30,
        27,
        26,
        26,
        17,
        17,
        24,
        25,
        23,
        25,
        18,
        18,
        21,
        20,
        15,
        16,
        16,
        20,
        16,
        16,
        24,
        24,
        19,
        22,
        22,
        20,
        19,
        21,
        18,
        18,
        17,
        17,
        13,
        13,
        13,
        9,
        9,
        10,
        10,
        9,
        9,
        12,
        12,
        13,
        14,
        14,
        14,
        13,
        14,
        16,
        16,
        16,
        16,
        17,
        14,
        14,
        15,
        13,
        10,
        11,
        12,
        12,
        13,
        12,
        12,
        12,
        9,
        9,
        9,
        9,
        10,
        10,
        11,
        11,
        8,
        9,
        9,
        5,
        6,
        5,
        5,
        5,
        3,
        3,
        5,
        4,
        4,
        4,
        8,
        8,
        12,
        12,
        11,
        11,
        8,
        8,
        8,
        8,
        10,
        12,
        11,
        11,
        11,
        9,
        8,
        8,
        8,
        9,
        10,
        6,
        6,
        9,
        4,
        2,
        2,
        2,
        2,
        3,
        2,
        2,
        1,
        1,
        2,
        2,
        2,
        6,
        4,
        4,
        16,
        14,
        14,
        17,
        15,
        18,
        18,
        13,
        18,
        15,
        16,
        15,
        15,
        15,
        11,
        10,
        14,
        15,
        10,
        14,
        16,
        16,
        21,
        21,
        23,
        28,
        23,
        30,
        30,
        30,
        31,
        31,
        29,
        29,
        31,
        28,
        30,
        29,
        29,
        31,
        26,
        23,
        23,
        21,
        24,
        21,
        20,
        20,
        17,
        21,
        24,
        24,
        23,
        24,
        24,
        22,
        24,
        27,
        27,
        27,
        26,
        26,
        27,
        24,
        24,
        17,
        22,
        18,
        25,
        21,
        19,
        19,
        25,
        22,
        24,
        23,
        24,
        25,
        25,
        27,
        24,
        26,
        26,
        28,
        24,
        23,
        23,
        21,
        21,
        22,
        24,
        23,
        23,
        32,
        32,
        29,
        32,
        27,
        26,
        23,
        33,
        33,
        37,
        37,
        40,
        46,
        45,
        43,
        41,
        41,
        46,
        46,
        51,
        54,
        61,
        61,
        60,
        61,
        53,
        62,
        55,
        59,
        59,
        62,
        68,
        68,
        75,
        62,
        62,
        69,
        61,
        61,
        51,
        51,
        51,
        50,
        49,
        51,
        51,
        47,
        45,
        45,
        47,
        51,
        40,
        40,
        40,
        40,
        37,
        41,
        48,
        48,
        46,
        46,
        38,
        47,
        44,
        44,
        46,
        52,
        48,
        48,
        48,
        49,
        42,
        43,
        42,
        39,
        40,
        40,
        39,
        39,
        37,
        36,
        41,
        39,
        43,
        37,
        42,
        42,
        39,
        42,
        43,
        35,
        34,
        34,
        37,
        37,
        34,
        39,
        35,
        37,
        37,
        30,
        34,
        34,
        34,
        35,
        34,
        34,
        34,
        40,
        44,
        36,
        36,
        32,
        38,
        36,
        41,
        41,
        40,
        40,
        39,
        39,
        32,
        35,
        35,
        35,
        33,
        33,
        39,
        39,
        40,
        40,
        43,
        40,
        38,
        40,
        38,
        38,
        36,
        37,
        38,
        38,
        37,
        37,
        37,
        40,
        40,
        37,
        40,
        38,
        38,
        42,
        39,
        39,
        39,
        40,
        37,
        38,
        44,
        44,
        48,
        51,
        51,
        58,
        58,
        55,
        52,
        52,
        57,
        62,
        62,
        62,
        68,
        68,
        62,
        62,
        67,
        69,
        79,
        79,
        75,
        81,
        81,
        79,
        78,
        78,
        74,
        74,
        83,
        87,
        83,
        87,
        85,
        87,
        87,
        86,
        81,
        81,
        79,
        77,
        77,
        77,
        77,
        80,
        86,
        87,
        87,
        83,
        77,
        85,
        77,
        85,
        90,
        83,
        94,
        94,
        97,
        99,
        104,
        98,
        100,
        98,
        97,
        97,
        92,
        90,
        103,
        103,
        98,
        98,
        107,
        103,
        106,
        106,
        106,
        93,
        88,
        89,
        90,
        90,
        90,
        90,
        93,
        97,
        94,
        94,
        94,
        98,
        101,
        101,
        92,
        98,
        97,
        100,
        99,
        105,
        100,
        100,
        80,
        85,
        89,
        81,
        81,
        79,
        79,
        75,
        75,
        83,
        81,
        73,
        81,
        78,
        78,
        74,
        83,
        71,
        67,
        74,
        65,
        66,
        64,
        64,
        55,
        57,
        63,
        55,
        58,
        61,
        61,
        61,
        65,
        56,
        52,
        59,
        59,
        66,
        66,
        63,
        60,
        60,
        64,
        63,
        58,
        63,
        63,
        60,
        60,
        63,
        58,
        53,
        53,
        52,
        52,
        55,
        55,
        49,
        48,
        49,
        43,
        49,
        45,
        51,
        52,
        48,
        58,
        58,
        54,
        68,
        74,
        77,
        70,
        70,
        75,
        76,
        75,
        68,
        70,
        70,
        74,
        79,
        73,
        75,
        75,
        70,
        70,
        71,
        72,
        72,
        68,
        68,
        58,
        64,
        62,
        62,
        62,
        67,
        72,
        73,
        77,
        71,
        71,
        71,
        64,
        68,
        68,
        63,
        65,
        65,
        65,
        68,
        68,
        66,
        61,
        61,
        69,
        68,
        72,
        70,
        77,
        69,
        63,
        63,
        71,
        81,
        68,
        68,
        80,
        78,
        78,
        70,
        72,
        69,
        62,
        69,
        66,
        66,
        64,
        78,
        71,
        61,
        67,
        67,
        64,
        74,
        74,
        76,
        76,
        83,
        79,
        79,
        74,
        74,
        75,
        80,
        70,
        74,
        74,
        88,
        77,
        77,
        91,
        86,
        86,
        88,
        88,
        89,
        91,
        79,
        81,
        81,
        78,
        81,
        81,
        87,
        87,
        88,
        87,
        87,
        79,
        79,
        78,
        76,
        82,
        88,
        76,
        77,
        77,
        80,
        85,
        81,
        81,
        78,
        78,
        77,
        74,
        78,
        75,
        71,
        69,
        69,
        78,
        77,
        77,
        72,
        82,
        76,
        82,
        82,
        78,
        78,
        75,
        73,
        73,
        75,
        79,
        85,
        81,
        79,
        85,
        85,
        81,
        85,
        80,
        88,
        84,
        90,
        90,
        79,
        83,
        83,
        77,
        77,
        81,
        81,
        80,
        90,
        90,
        81,
        84,
        84,
        82,
        82,
        86,
        82,
        78,
        75,
        79,
        79,
        75,
        75,
        81,
        81,
        83,
        91,
        103,
        95,
        101,
        98,
        94,
        94,
        95,
        84,
        90,
        90,
        92,
        99,
        93,
        103,
        98,
        98,
        88,
        95,
        93,
        93,
        96,
        95,
        94,
        101,
        107,
        107,
        112,
        116,
        114,
        114,
        114,
        114,
        117,
        117,
        120,
        115,
        120,
        122,
        139,
        139,
        119,
        124,
        108,
        113,
        119,
        119,
        115,
        118,
        120,
        120,
        131,
        131,
        128,
        128,
        117,
        123,
        123,
        112,
        112,
        119,
        120,
        115,
        115,
        114,
        113,
        113,
        110,
        108,
        114,
        116,
        102,
        102,
        96,
        93,
        88,
        94,
        88,
        90,
        87,
        84,
        83,
        89,
        74,
        74,
        80,
        80,
        85,
        85,
        94,
        88,
        88,
        86,
        100,
        91,
        84,
        84,
        84,
        91,
        90,
        83,
        95,
        96,
        96,
        101,
        103,
        104,
        101,
        101,
        97,
        97,
        106,
        106,
        96,
        99,
        95,
        87,
        87,
        95,
        87,
        100,
        100,
        110,
        106,
        120,
        131,
        131,
        129,
        135,
        135,
        146,
        146,
        136,
        146,
        151,
        154,
        158,
        164,
        164,
        157,
        157,
        151,
        152,
        157,
        156,
        146,
        142,
        148,
        148,
        139,
        139,
        140,
        146,
        125,
        138,
        133,
        133,
        136,
        134,
        144,
        134,
        134,
        144,
        144,
        142,
        149,
        149,
        140,
        146,
        150,
        144,
        148,
        148,
        136,
        134,
        131,
        134,
        134,
        133,
        141,
        127,
        127,
        122,
        113,
        104,
        114,
        118,
        124,
        124,
        125,
        125,
        125,
        125,
        116,
        128,
        124,
        124,
        116,
        127,
        133,
        133,
        136,
        147,
        140,
        137,
        151,
        151,
        140,
        137,
        136,
        134,
        134,
        140,
        140,
        140,
        133,
        133,
        121,
        121,
        132,
        132,
        136,
        136,
        134,
        129,
        131,
        131,
        128,
        128,
        126,
        126,
        127,
        127,
        131,
        129,
        142,
        147,
        147,
        146,
        145,
        145,
        153,
        139,
        154,
        137,
        139,
        139,
        129,
        129,
        130,
        0,
        125,
        115,
        122,
        122,
        125,
        120,
        120,
        126,
        107,
        117,
        117,
        119,
        115,
        105,
        103,
        103,
        112,
        103,
        122,
        122,
        113,
        115,
        110,
        115,
        118,
        113,
        118,
        119,
        116,
        116,
        126,
        114,
        118,
        118,
        123,
        123,
        130,
        136,
        125,
        128,
        125,
        117,
        120,
        128,
        126,
        126,
        128,
        131,
        131,
        124,
        125,
        124,
        118,
        118,
        122,
        122,
        118,
        118,
        110,
        110,
        103,
        108,
        106,
        102,
        109,
        104,
        105,
        105,
        97,
        99,
        96,
        104,
        104,
        97,
        92,
        93,
        94,
        94,
        100,
        89,
        89,
        86,
        80,
        86,
        78,
        78,
        89,
        82,
        84,
        84,
        75,
        75,
        76,
        83,
        77,
        77,
        87,
        87,
        71,
        71,
        76,
        90,
        77,
        93,
        88,
        87,
        87,
        90,
        98,
        94,
        91
      ],
      "step": 60
    },
    "timestamp": "2025-11-20T22:06:58.756Z"
  },
  "stats_7d": {
    "success": true,
    "data": {
      "from": "2025-11-13T23:00:00.000Z",
      "to": "2025-11-20T22:06:00.000Z",
      "stats": [
        141,
        151,
        180,
        203,
        209,
        163,
        102,
        118,
        110,
        90,
        61,
        63,
        56,
        57,
        51,
        60,
        65,
        49,
        65,
        65,
        50,
        61,
        82,
        118,
        156,
        141,
        162,
        160,
        124,
        123,
        103,
        114,
        121,
        117,
        142,
        178,
        187,
        202,
        246,
        260,
        237,
        279,
        240,
        243,
        274,
        260,
        257,
        252,
        225,
        215,
        188,
        180,
        187,
        200,
        203,
        209,
        225,
        194,
        190,
        157,
        139,
        145,
        152,
        134,
        94,
        84,
        100,
        95,
        126,
        162,
        157,
        171,
        166,
        204,
        184,
        149,
        170,
        192,
        232,
        249,
        239,
        242,
        241,
        229,
        266,
        298,
        305,
        314,
        274,
        239,
        244,
        196,
        234,
        269,
        265,
        268,
        260,
        234,
        228,
        198,
        191,
        194,
        198,
        192,
        187,
        179,
        171,
        162,
        136,
        110,
        104,
        83,
        58,
        62,
        88,
        86,
        75,
        97,
        103,
        117,
        125,
        151,
        182,
        176,
        173,
        166,
        185,
        213,
        242,
        245,
        265,
        285,
        258,
        285,
        297,
        291,
        273,
        277,
        275,
        229,
        230,
        180,
        189,
        188,
        177,
        185,
        185,
        185,
        158,
        139,
        156,
        131,
        125,
        112,
        109,
        92,
        57,
        40,
        26,
        32,
        46,
        44,
        37,
        39,
        51,
        42,
        42,
        45,
        42,
        45,
        79,
        76,
        77,
        75,
        81,
        87,
        91,
        108,
        110,
        121,
        144,
        155,
        193,
        170,
        185,
        157,
        145,
        131,
        102,
        104,
        97,
        100,
        116,
        136,
        141,
        123,
        125,
        134,
        160,
        141,
        111,
        80,
        61,
        54,
        18,
        7,
        18,
        18,
        23,
        22,
        38,
        41,
        21,
        40,
        43,
        37,
        55,
        75,
        91,
        89,
        88,
        95,
        87,
        72,
        74,
        92,
        86,
        84,
        89,
        108,
        111,
        137,
        148,
        141,
        128,
        118,
        92,
        97,
        128,
        98,
        91,
        88,
        105,
        136,
        129,
        127,
        137,
        136,
        90,
        66,
        41,
        40,
        42,
        20,
        20,
        37,
        27,
        38,
        43,
        42,
        24,
        0,
        0,
        9,
        27,
        39,
        39,
        56,
        65,
        74,
        54,
        45,
        59,
        61,
        70,
        91,
        110,
        109,
        119,
        126,
        114,
        117,
        110,
        76,
        71,
        74,
        87,
        75,
        79,
        99,
        99,
        114,
        107,
        111,
        95,
        78,
        63,
        38,
        25,
        17,
        12,
        12,
        30,
        31,
        28,
        62,
        75,
        52,
        44,
        43,
        69,
        87,
        107,
        105,
        83,
        68,
        79,
        81,
        88,
        91,
        85,
        90,
        103,
        139,
        123,
        106,
        164,
        150,
        147,
        151,
        154,
        136,
        131,
        100,
        98
      ],
      "average_stats": [
        127,
        132,
        155,
        187,
        193,
        127,
        92,
        105,
        96,
        59,
        53,
        55,
        51,
        46,
        42,
        49,
        59,
        38,
        49,
        51,
        44,
        48,
        62,
        92,
        130,
        126,
        150,
        135,
        111,
        92,
        81,
        97,
        109,
        107,
        121,
        158,
        165,
        186,
        206,
        236,
        225,
        251,
        206,
        200,
        252,
        245,
        237,
        215,
        213,
        171,
        167,
        145,
        164,
        173,
        189,
        174,
        200,
        175,
        146,
        138,
        127,
        131,
        134,
        108,
        83,
        71,
        88,
        79,
        108,
        143,
        135,
        156,
        146,
        174,
        160,
        127,
        147,
        166,
        209,
        229,
        222,
        210,
        213,
        214,
        232,
        275,
        288,
        275,
        248,
        223,
        222,
        164,
        183,
        247,
        242,
        242,
        241,
        204,
        200,
        169,
        168,
        177,
        186,
        174,
        155,
        163,
        151,
        148,
        117,
        101,
        81,
        64,
        47,
        51,
        73,
        73,
        64,
        83,
        90,
        97,
        112,
        137,
        162,
        167,
        158,
        150,
        170,
        185,
        219,
        225,
        243,
        256,
        237,
        260,
        262,
        256,
        252,
        255,
        247,
        213,
        205,
        160,
        175,
        157,
        156,
        157,
        164,
        157,
        133,
        125,
        139,
        109,
        106,
        89,
        94,
        69,
        43,
        30,
        22,
        27,
        37,
        37,
        26,
        27,
        41,
        35,
        31,
        36,
        32,
        36,
        61,
        64,
        61,
        66,
        72,
        80,
        82,
        89,
        91,
        105,
        125,
        131,
        170,
        160,
        165,
        117,
        127,
        116,
        79,
        91,
        86,
        83,
        103,
        118,
        124,
        114,
        101,
        106,
        145,
        127,
        97,
        63,
        51,
        31,
        14,
        5,
        13,
        15,
        17,
        16,
        28,
        28,
        16,
        30,
        35,
        31,
        47,
        69,
        79,
        66,
        79,
        83,
        62,
        61,
        68,
        79,
        71,
        73,
        82,
        91,
        87,
        121,
        136,
        126,
        110,
        97,
        79,
        82,
        109,
        83,
        77,
        72,
        91,
        120,
        113,
        104,
        125,
        111,
        69,
        56,
        31,
        27,
        31,
        9,
        14,
        27,
        17,
        25,
        34,
        34,
        5,
        0,
        0,
        1,
        17,
        29,
        32,
        44,
        52,
        60,
        43,
        39,
        43,
        44,
        61,
        78,
        87,
        87,
        110,
        113,
        103,
        106,
        96,
        60,
        60,
        54,
        75,
        68,
        69,
        83,
        81,
        99,
        93,
        95,
        77,
        63,
        43,
        29,
        18,
        13,
        8,
        6,
        18,
        25,
        23,
        41,
        53,
        43,
        37,
        38,
        51,
        81,
        95,
        91,
        66,
        55,
        70,
        69,
        72,
        83,
        77,
        83,
        92,
        119,
        103,
        93,
        131,
        141,
        127,
        133,
        126,
        118,
        113,
        84,
        91
      ],
      "step": 1800
    },
    "timestamp": "2025-11-20T22:07:01.327Z"
  },
  "fetched_at": "2025-11-20T22:07:01.280956Z"
}