{
  "map_code": "0038-9297-7629",
  "map_data": {
    "success": true,
    "data": {
      "attributions": [],
      "ccu_record": 346,
      "ccu_record_date": "2025-10-19T17:00:00.000Z",
      "created": "2025-10-15T16:37:56.823Z",
      "discovery_intent": "PUBLIC",
      "id": "0038-9297-7629",
      "image_url": "https://cdn-0001.qstv.on.epicgames.com/cEAtIfaSdfHTUqAnMA/image/landscape_comp.jpeg",
      "image_url_cohort_b": null,
      "introduction": "\n\n",
      "lastSyncCcu": 0,
      "lastSyncDate": "2025-11-19T21:50:00.000Z",
      "lastSyncDisabled": false,
      "lobby_background_image_url": null,
      "locale": "en",
      "max_players": 6,
      "metrics_day_id": 453,
      "metrics_minute_id": 475,
      "metrics_updated_date": "2025-11-19T19:07:23.864Z",
      "minutes_played": 1343041,
      "minutes_played_sync_date": "2025-11-19T03:14:24.060Z",
      "moderation_status": "Approved",
      "name": "MANSION ESCAPE",
      "owner_code": "goodgamers",
      "owner_name": "GoodGamesStudio",
      "published": "2025-09-27T03:00:19.227Z",
      "ratings": [
        "ACB_AGE_PG",
        "PEGI_AGE_7",
        "GEN_AGE_7",
        "CLASSIND_AGE_LIVRE",
        "USK_AGE_6",
        "GRAC_AGE_ALL",
        "ESRB_AGE_E10",
        "RUSSIA_AGE_16"
      ],
      "square_image_url": null,
      "state": "no_discovery",
      "tagline": "\ud83d\udddd Search for Keys to Escape the Haunted Mansion\n\u2694 1 Hunter: Find and eliminate the Survivors\n\ud83c\udfc3\u200d\u2642\ufe0f 5 Survivors: Find a key and escape the Mansion\n\ud83e\uddf1 Discover Bricks to Build Walls\n\ud83d\udc65 Fun with Friends",
      "tags": [
        "party game",
        "just for fun",
        "role playing",
        "survival horror"
      ],
      "type": "lego",
      "version": 5,
      "xp_enabled": false,
      "creator": {
        "id": "goodgamers",
        "last_sync_ccu": 13872,
        "last_sync_minutes_played": 18541602463,
        "last_sync_minutes_played_position": 7,
        "last_sync_position": 6,
        "lookup_avatar": "https://cdn-0001.qstv.on.epicgames.com/05s2x23UXyuSqmJ0Hv5YL6/image.jpg",
        "lookup_banner": "https://cdn-0001.qstv.on.epicgames.com/05gZACoPvRA8njGcTYEpA3/image.jpg",
        "lookup_bio": "Creating your favorite games | Murder Mystery, Bed Wars, Go Goated\n\ud83d\udd3d Join our Discord!",
        "lookup_display_name": "goodgamers",
        "lookup_follower_count": 2044498,
        "lookup_socials_discord": "goodgamers",
        "lookup_socials_instagram": "goodgamersfn",
        "lookup_socials_twitter": "goodgamers",
        "lookup_socials_youtube": "@goodgamersorg",
        "name": "GoodGamesStudio"
      }
    },
    "timestamp": "2025-11-19T22:37:02.118Z"
  },
  "stats": {
    "stats_7d": {
      "success": true,
      "data": {
        "from": "2025-11-12T23:30:00.000Z",
        "to": "2025-11-19T22:30:00.000Z",
        "stats": [
          38,
          41,
          35,
          35,
          33,
          25,
          31,
          19,
          21,
          17,
          14,
          11,
          14,
          3,
          5,
          9,
          14,
          9,
          8,
          7,
          11,
          17,
          7,
          5,
          7,
          15,
          16,
          14,
          14,
          22,
          11,
          22,
          14,
          4,
          4,
          5,
          7,
          8,
          8,
          4,
          5,
          13,
          4,
          6,
          8,
          8,
          5,
          6,
          6,
          10,
          12,
          3,
          3,
          3,
          5,
          4,
          3,
          1,
          2,
          1,
          1,
          3,
          3,
          5,
          5,
          5,
          3,
          2,
          0,
          0,
          1,
          1,
          3,
          0,
          4,
          4,
          1,
          1,
          2,
          7,
          5,
          4,
          4,
          5,
          7,
          5,
          4,
          5,
          4,
          4,
          6,
          5,
          4,
          11,
          13,
          7,
          5,
          5,
          11,
          18,
          12,
          13,
          9,
          11,
          8,
          6,
          5,
          4,
          3,
          6,
          6,
          5,
          3,
          5,
          5,
          3,
          3,
          2,
          5,
          8,
          8,
          7,
          11,
          9,
          16,
          19,
          17,
          12,
          15,
          11,
          14,
          10,
          10,
          12,
          16,
          18,
          16,
          15,
          10,
          11,
          16,
          21,
          14,
          11,
          10,
          12,
          12,
          9,
          13,
          15,
          14,
          15,
          8,
          4,
          10,
          11,
          9,
          8,
          3,
          3,
          3,
          8,
          8,
          3,
          9,
          5,
          3,
          7,
          11,
          10,
          13,
          9,
          17,
          17,
          20,
          19,
          21,
          16,
          14,
          15,
          11,
          15,
          15,
          18,
          17,
          18,
          17,
          13,
          15,
          13,
          12,
          12,
          10,
          10,
          8,
          8,
          2,
          2,
          2,
          4,
          5,
          3,
          5,
          1,
          1,
          0,
          4,
          3,
          0,
          1,
          1,
          5,
          5,
          1,
          0,
          0,
          1,
          1,
          3,
          2,
          1,
          2,
          3,
          7,
          4,
          1,
          1,
          2,
          5,
          2,
          5,
          3,
          2,
          6,
          1,
          1,
          3,
          3,
          1,
          2,
          3,
          6,
          2,
          6,
          5,
          2,
          1,
          5,
          1,
          2,
          0,
          0,
          2,
          2,
          1,
          1,
          1,
          1,
          1,
          2,
          0,
          0,
          0,
          2,
          1,
          1,
          0,
          2,
          5,
          2,
          3,
          1,
          2,
          1,
          5,
          2,
          4,
          2,
          0,
          1,
          1,
          5,
          2,
          5,
          2,
          4,
          3,
          7,
          8,
          2,
          4,
          4,
          4,
          2,
          2,
          1,
          1,
          3,
          1,
          5,
          2,
          1,
          1,
          0,
          0,
          0,
          0,
          0,
          0,
          0,
          0,
          0,
          0,
          0,
          0,
          1,
          0,
          4,
          0,
          2,
          2,
          0,
          2,
          1,
          2,
          2,
          2,
          3,
          1,
          0,
          0,
          1,
          1,
          0,
          0
        ],
        "average_stats": [
          31,
          32,
          26,
          22,
          22,
          20,
          25,
          11,
          13,
          12,
          10,
          6,
          6,
          1,
          3,
          5,
          9,
          4,
          3,
          4,
          5,
          10,
          4,
          2,
          4,
          9,
          11,
          6,
          10,
          13,
          6,
          14,
          6,
          2,
          3,
          2,
          4,
          5,
          4,
          1,
          1,
          6,
          1,
          2,
          4,
          5,
          3,
          2,
          3,
          3,
          6,
          1,
          1,
          1,
          2,
          1,
          2,
          0,
          0,
          0,
          0,
          0,
          1,
          4,
          4,
          2,
          2,
          0,
          0,
          0,
          0,
          0,
          1,
          0,
          2,
          3,
          0,
          0,
          1,
          4,
          3,
          2,
          1,
          2,
          3,
          2,
          2,
          1,
          2,
          2,
          3,
          3,
          1,
          4,
          7,
          4,
          2,
          2,
          6,
          11,
          6,
          11,
          5,
          7,
          5,
          4,
          2,
          2,
          1,
          2,
          1,
          2,
          1,
          3,
          1,
          1,
          2,
          1,
          2,
          2,
          5,
          4,
          5,
          5,
          7,
          13,
          13,
          8,
          9,
          7,
          8,
          7,
          5,
          7,
          10,
          8,
          12,
          8,
          6,
          8,
          11,
          11,
          8,
          7,
          5,
          7,
          6,
          5,
          7,
          11,
          8,
          7,
          5,
          2,
          2,
          5,
          5,
          6,
          1,
          1,
          1,
          4,
          3,
          1,
          4,
          2,
          1,
          3,
          6,
          6,
          11,
          4,
          7,
          10,
          11,
          12,
          14,
          11,
          11,
          9,
          8,
          11,
          10,
          13,
          11,
          12,
          11,
          7,
          9,
          8,
          8,
          8,
          5,
          6,
          3,
          3,
          1,
          0,
          0,
          1,
          3,
          1,
          1,
          0,
          0,
          0,
          1,
          1,
          0,
          0,
          1,
          4,
          2,
          0,
          0,
          0,
          0,
          0,
          1,
          1,
          0,
          0,
          0,
          3,
          1,
          0,
          0,
          0,
          2,
          1,
          1,
          1,
          0,
          4,
          0,
          0,
          0,
          1,
          0,
          1,
          1,
          1,
          0,
          2,
          1,
          1,
          1,
          2,
          1,
          0,
          0,
          0,
          0,
          1,
          1,
          0,
          0,
          0,
          1,
          0,
          0,
          0,
          0,
          0,
          0,
          0,
          0,
          0,
          1,
          1,
          1,
          0,
          0,
          0,
          1,
          0,
          2,
          1,
          0,
          0,
          0,
          3,
          0,
          1,
          0,
          2,
          0,
          1,
          3,
          0,
          1,
          2,
          2,
          1,
          1,
          0,
          0,
          2,
          1,
          3,
          0,
          0,
          0,
          0,
          0,
          0,
          0,
          0,
          0,
          0,
          0,
          0,
          0,
          0,
          0,
          0,
          0,
          1,
          0,
          1,
          1,
          0,
          1,
          1,
          1,
          1,
          1,
          2,
          0,
          0,
          0,
          0,
          0,
          0,
          0
        ],
        "step": 1800
      },
      "timestamp": "2025-11-19T22:37:06.908Z"
    }
  },
  "fetched_at": "2025-11-19T22:37:06.915988Z"
}