{
  "map_code": "1325-4790-8517",
  "map_data": {
    "attributions": [
      {
        "author": "Aullwen",
        "license": "Creative Commons Attribution",
        "title": "Glass Bottle"
      },
      {
        "author": "Kedar Phansikar",
        "license": "Creative Commons Attribution",
        "title": "Buggati"
      },
      {
        "author": "TheGuy",
        "license": "Creative Commons Attribution",
        "title": "Low-Poly Brick Wall"
      },
      {
        "author": "alpthepalp",
        "license": "Creative Commons Attribution",
        "title": "NUKE"
      },
      {
        "author": "thelegokid4455",
        "license": "Creative Commons Attribution",
        "title": "Low Poly Wooden Fence"
      },
      {
        "author": "Amythyst Morris",
        "license": "Creative Commons Attribution",
        "title": "Caged"
      },
      {
        "author": "CGPlayz",
        "license": "Creative Commons Attribution",
        "title": "Troll face"
      },
      {
        "author": "barkovskis",
        "license": "Creative Commons Attribution",
        "title": "Pepe head"
      }
    ],
    "ccu_record": 1477,
    "ccu_record_date": "2025-11-08T18:30:00.000Z",
    "created": "2025-11-15T16:36:11.631Z",
    "discovery_intent": "PUBLIC",
    "id": "1325-4790-8517",
    "image_url": "https://cdn-0001.qstv.on.epicgames.com/NlsiIXeVEmWsyzGsmJ/image/landscape_comp.jpeg",
    "image_url_cohort_b": null,
    "introduction": "\ud83e\udde0 Play as a BRAINROT TikTok Meme\n\ud83e\uddb8 40+ Unique Brainrot Powers\n\ud83c\udf89 Last Updated: 11/8\ud83c\udf89",
    "lastSyncCcu": 48,
    "lastSyncDate": "2025-11-20T21:29:00.000Z",
    "lastSyncDisabled": false,
    "lobby_background_image_url": null,
    "locale": "en",
    "max_players": 12,
    "metrics_day_id": 455,
    "metrics_minute_id": 477,
    "metrics_updated_date": "2025-11-20T20:05:59.546Z",
    "minutes_played": 814790,
    "minutes_played_sync_date": "2025-11-16T10:17:49.983Z",
    "moderation_status": "Approved",
    "name": "\ud83e\udde0BRAINROT BOX PVP/BOXFIGHTS \ud83d\ude02BOX PVP\ud83d\udce6",
    "owner_code": "real_moad",
    "owner_name": "Real_Moad",
    "published": "2025-10-21T12:22:10.654Z",
    "ratings": [
      "ACB_AGE_PG",
      "PEGI_AGE_7",
      "GEN_AGE_7",
      "CLASSIND_AGE_10",
      "USK_AGE_12",
      "GRAC_AGE_ALL",
      "ESRB_AGE_T",
      "RUSSIA_AGE_16"
    ],
    "square_image_url": null,
    "state": "in_discovery",
    "tagline": "\ud83e\udde0 BRAINROT Boxfights With The Most Crazy Memes\n\ud83e\uddb8 41+ Unique Brainrot Powers\n\n\u2764\ufe0f\u200d\ud83e\ude79 W SPEED - Trap Player in a Bottle\n\ud83d\udcdd JOB - Jumpscare\n\u2708\ufe0f HOLIDAY - Change map to Bounce\n\n\ud83e\udde0 Play as a BRAINROT TikTok Meme\n\ud83c\udf89 Last Updated: 11/8\ud83c\udf89",
    "tags": [
      "boxfight",
      "memes",
      "pvp",
      "practice"
    ],
    "type": "uefn",
    "version": 13,
    "xp_enabled": true,
    "creator": {
      "id": "real_moad",
      "last_sync_ccu": 52,
      "last_sync_minutes_played": 5449145,
      "last_sync_minutes_played_position": 2634,
      "last_sync_position": 572,
      "lookup_avatar": "https://cdn-0001.qstv.on.epicgames.com/06C9K5GPlfkf9pSqy3i2UT/image.jpg",
      "lookup_banner": "https://cdn2.unrealengine.com/t-ui-creatorprofile-banner-fallbackerror-1920x1080-3f830cc95018.png",
      "lookup_bio": "Hi i like creating fun experience for you and your friends to enjoy!",
      "lookup_display_name": "real_moad",
      "lookup_follower_count": 575,
      "lookup_socials_instagram": "real_moad/",
      "lookup_socials_youtube": "https://www.youtube.com/@Moad_fn",
      "name": "Real_Moad"
    }
  },
  "stats_24h": {
    "success": true,
    "data": {
      "from": "2025-11-19T22:12:00.000Z",
      "to": "2025-11-20T22:09:00.000Z",
      "stats": [
        0,
        0,
        0,
        0,
        1,
        1,
        1,
        1,
        0,
        0,
        0,
        1,
        1,
        1,
        1,
        2,
        1,
        3,
        3,
        3,
        3,
        3,
        5,
        4,
        4,
        3,
        3,
        3,
        5,
        4,
        3,
        3,
        2,
        3,
        1,
        2,
        2,
        2,
        2,
        2,
        2,
        2,
        2,
        2,
        3,
        6,
        7,
        7,
        10,
        10,
        10,
        9,
        14,
        14,
        10,
        11,
        8,
        8,
        11,
        11,
        8,
        8,
        13,
        15,
        12,
        12,
        10,
        14,
        9,
        11,
        13,
        13,
        13,
        13,
        14,
        17,
        13,
        13,
        10,
        10,
        12,
        14,
        14,
        15,
        15,
        16,
        12,
        12,
        12,
        12,
        10,
        11,
        8,
        8,
        7,
        8,
        10,
        9,
        7,
        7,
        4,
        5,
        8,
        8,
        7,
        7,
        9,
        12,
        10,
        10,
        13,
        12,
        13,
        13,
        8,
        8,
        8,
        9,
        5,
        5,
        0,
        3,
        3,
        2,
        4,
        4,
        3,
        3,
        5,
        4,
        5,
        3,
        4,
        4,
        9,
        8,
        9,
        9,
        10,
        10,
        12,
        12,
        12,
        13,
        13,
        7,
        11,
        11,
        10,
        8,
        11,
        11,
        11,
        11,
        10,
        9,
        10,
        8,
        14,
        9,
        11,
        11,
        9,
        9,
        5,
        7,
        9,
        7,
        6,
        6,
        7,
        7,
        9,
        15,
        15,
        15,
        19,
        19,
        21,
        15,
        15,
        25,
        32,
        32,
        24,
        26,
        27,
        27,
        33,
        33,
        26,
        26,
        30,
        27,
        27,
        40,
        34,
        34,
        32,
        26,
        30,
        24,
        24,
        23,
        21,
        21,
        16,
        16,
        16,
        19,
        22,
        19,
        19,
        19,
        20,
        20,
        20,
        19,
        20,
        15,
        15,
        17,
        18,
        18,
        18,
        23,
        24,
        24,
        21,
        21,
        22,
        17,
        17,
        19,
        20,
        20,
        22,
        22,
        18,
        18,
        18,
        26,
        18,
        24,
        16,
        14,
        14,
        21,
        20,
        20,
        20,
        14,
        15,
        17,
        17,
        16,
        17,
        17,
        9,
        14,
        10,
        11,
        8,
        12,
        8,
        8,
        8,
        8,
        8,
        9,
        10,
        10,
        9,
        9,
        9,
        9,
        15,
        15,
        13,
        17,
        15,
        19,
        19,
        18,
        18,
        14,
        13,
        13,
        16,
        16,
        14,
        14,
        16,
        17,
        22,
        22,
        18,
        17,
        16,
        16,
        15,
        15,
        18,
        18,
        43,
        43,
        55,
        77,
        96,
        96,
        113,
        113,
        112,
        141,
        155,
        205,
        209,
        209,
        239,
        239,
        250,
        250,
        250,
        271,
        275,
        249,
        266,
        266,
        221,
        221,
        199,
        179,
        192,
        164,
        157,
        157,
        148,
        132,
        124,
        143,
        117,
        117,
        103,
        108,
        108,
        103,
        100,
        100,
        102,
        102,
        128,
        121,
        121,
        135,
        131,
        136,
        136,
        151,
        149,
        149,
        161,
        170,
        166,
        186,
        170,
        191,
        189,
        172,
        173,
        173,
        148,
        144,
        133,
        107,
        121,
        121,
        99,
        103,
        82,
        82,
        89,
        68,
        68,
        68,
        71,
        85,
        85,
        77,
        91,
        121,
        126,
        130,
        143,
        143,
        164,
        180,
        201,
        201,
        229,
        215,
        232,
        255,
        240,
        260,
        249,
        247,
        247,
        247,
        227,
        227,
        221,
        188,
        183,
        183,
        165,
        165,
        149,
        142,
        135,
        135,
        128,
        126,
        126,
        100,
        100,
        83,
        83,
        85,
        70,
        70,
        60,
        54,
        48,
        48,
        45,
        45,
        44,
        44,
        41,
        42,
        49,
        49,
        39,
        36,
        33,
        31,
        32,
        32,
        26,
        30,
        30,
        32,
        29,
        29,
        29,
        23,
        21,
        24,
        22,
        22,
        28,
        28,
        29,
        23,
        27,
        20,
        20,
        19,
        16,
        16,
        16,
        18,
        22,
        15,
        16,
        16,
        15,
        14,
        14,
        9,
        9,
        9,
        7,
        7,
        6,
        8,
        5,
        8,
        6,
        6,
        5,
        5,
        5,
        6,
        8,
        7,
        8,
        11,
        8,
        9,
        8,
        11,
        11,
        10,
        10,
        11,
        11,
        9,
        13,
        13,
        6,
        10,
        4,
        4,
        8,
        9,
        9,
        7,
        9,
        9,
        8,
        9,
        8,
        6,
        8,
        9,
        6,
        8,
        8,
        8,
        10,
        10,
        11,
        10,
        10,
        13,
        13,
        13,
        12,
        9,
        12,
        11,
        11,
        12,
        12,
        14,
        14,
        15,
        11,
        11,
        9,
        10,
        7,
        7,
        4,
        4,
        4,
        12,
        6,
        6,
        7,
        7,
        7,
        8,
        8,
        10,
        7,
        12,
        8,
        8,
        7,
        7,
        5,
        5,
        3,
        5,
        5,
        3,
        5,
        5,
        4,
        3,
        3,
        3,
        2,
        3,
        3,
        2,
        3,
        3,
        2,
        2,
        5,
        4,
        8,
        6,
        5,
        5,
        3,
        3,
        7,
        7,
        7,
        5,
        5,
        8,
        8,
        8,
        4,
        4,
        10,
        6,
        10,
        9,
        5,
        9,
        11,
        8,
        9,
        6,
        6,
        7,
        6,
        6,
        4,
        5,
        5,
        3,
        2,
        2,
        0,
        0,
        2,
        6,
        6,
        6,
        5,
        5,
        3,
        1,
        1,
        1,
        2,
        2,
        2,
        3,
        6,
        3,
        1,
        1,
        0,
        0,
        0,
        0,
        0,
        2,
        4,
        4,
        3,
        3,
        4,
        4,
        3,
        2,
        2,
        4,
        0,
        0,
        0,
        0,
        0,
        0,
        0,
        0,
        0,
        2,
        2,
        2,
        2,
        4,
        4,
        2,
        3,
        2,
        3,
        3,
        5,
        5,
        2,
        2,
        2,
        2,
        2,
        0,
        0,
        1,
        0,
        0,
        0,
        0,
        0,
        1,
        1,
        0,
        0,
        0,
        0,
        0,
        1,
        1,
        1,
        1,
        4,
        4,
        5,
        4,
        4,
        4,
        4,
        4,
        4,
        2,
        2,
        3,
        3,
        3,
        3,
        4,
        1,
        1,
        1,
        1,
        0,
        0,
        0,
        1,
        2,
        2,
        3,
        3,
        3,
        3,
        2,
        2,
        2,
        2,
        2,
        2,
        2,
        2,
        2,
        1,
        0,
        0,
        0,
        0,
        0,
        0,
        0,
        0,
        0,
        0,
        2,
        2,
        3,
        3,
        3,
        4,
        3,
        3,
        3,
        3,
        2,
        3,
        4,
        3,
        5,
        5,
        5,
        5,
        1,
        0,
        0,
        0,
        0,
        0,
        0,
        0,
        0,
        0,
        0,
        0,
        4,
        3,
        2,
        3,
        3,
        2,
        1,
        1,
        2,
        0,
        0,
        0,
        0,
        0,
        0,
        2,
        3,
        3,
        3,
        4,
        4,
        3,
        6,
        6,
        2,
        4,
        3,
        3,
        3,
        7,
        7,
        5,
        5,
        6,
        5,
        5,
        7,
        7,
        7,
        5,
        5,
        9,
        8,
        11,
        11,
        11,
        9,
        9,
        9,
        6,
        6,
        5,
        8,
        8,
        0,
        0,
        0,
        0,
        0,
        0,
        0,
        0,
        2,
        2,
        2,
        2,
        2,
        2,
        2,
        2,
        2,
        4,
        4,
        4,
        5,
        3,
        3,
        3,
        3,
        4,
        3,
        3,
        5,
        2,
        2,
        2,
        0,
        0,
        1,
        0,
        0,
        0,
        0,
        1,
        1,
        1,
        5,
        5,
        3,
        3,
        3,
        3,
        6,
        3,
        6,
        6,
        8,
        6,
        2,
        2,
        10,
        10,
        10,
        0,
        0,
        0,
        0,
        0,
        2,
        1,
        1,
        1,
        3,
        3,
        10,
        9,
        9,
        9,
        8,
        8,
        2,
        3,
        3,
        2,
        3,
        4,
        5,
        3,
        5,
        7,
        10,
        10,
        10,
        11,
        14,
        15,
        10,
        10,
        9,
        12,
        9,
        12,
        10,
        10,
        8,
        8,
        7,
        7,
        6,
        6,
        6,
        5,
        6,
        6,
        6,
        7,
        7,
        7,
        2,
        2,
        3,
        3,
        4,
        2,
        3,
        3,
        4,
        2,
        2,
        4,
        3,
        6,
        3,
        2,
        3,
        3,
        5,
        5,
        4,
        7,
        5,
        4,
        5,
        5,
        4,
        6,
        3,
        4,
        6,
        5,
        4,
        3,
        3,
        3,
        4,
        4,
        6,
        5,
        5,
        6,
        7,
        8,
        6,
        6,
        7,
        7,
        7,
        6,
        7,
        8,
        6,
        4,
        4,
        4,
        4,
        4,
        3,
        3,
        3,
        3,
        5,
        6,
        2,
        1,
        1,
        0,
        2,
        5,
        8,
        8,
        8,
        8,
        10,
        10,
        13,
        13,
        12,
        12,
        12,
        15,
        14,
        17,
        17,
        17,
        17,
        17,
        29,
        22,
        29,
        21,
        26,
        23,
        29,
        24,
        26,
        27,
        31,
        31,
        31,
        26,
        28,
        28,
        28,
        34,
        34,
        35,
        34,
        34,
        34,
        34,
        21,
        21,
        25,
        19,
        23,
        23,
        23,
        23,
        23,
        22,
        21,
        24,
        30,
        30,
        31,
        26,
        27,
        27,
        30,
        34,
        40,
        42,
        40,
        40,
        39,
        39,
        39,
        39,
        34,
        27,
        40,
        41,
        43,
        43,
        46,
        45,
        56,
        56,
        59,
        46,
        42,
        46,
        46,
        32,
        31,
        31,
        33,
        33,
        38,
        40,
        44,
        45,
        42,
        48,
        42,
        42,
        39,
        39,
        42,
        50,
        51,
        49,
        36,
        36,
        45,
        38,
        33,
        39,
        32,
        32,
        31,
        32,
        32,
        23,
        30,
        30,
        24,
        24,
        21,
        21,
        18,
        20,
        24,
        24,
        22,
        18,
        18,
        28,
        28,
        33,
        33,
        36,
        34,
        32,
        35,
        35,
        32,
        34,
        24,
        24,
        18,
        20,
        15,
        14,
        14,
        13,
        22,
        22,
        13,
        15,
        14,
        14,
        16,
        23,
        23,
        26,
        22,
        22,
        22,
        20,
        23,
        23,
        27,
        27,
        24,
        25,
        24,
        23,
        23,
        17,
        20,
        16,
        12,
        12,
        16,
        26,
        31,
        30,
        30,
        28,
        28,
        32,
        32,
        32,
        37,
        37,
        34,
        34,
        30,
        28,
        30,
        32,
        32,
        22,
        25,
        21,
        17,
        17,
        16,
        16,
        16,
        13,
        11,
        11,
        11,
        11,
        10,
        10,
        14,
        14,
        12,
        12,
        12,
        14,
        16,
        13,
        17,
        17,
        15,
        14,
        14,
        20,
        14,
        17,
        17,
        17,
        20,
        17,
        18,
        18,
        19,
        18,
        18,
        11,
        11,
        12,
        12,
        12,
        12,
        9,
        9,
        9,
        11,
        11,
        12,
        12,
        20,
        16,
        20,
        19,
        19,
        21,
        20,
        20,
        31,
        35,
        33,
        32,
        32,
        40,
        37,
        37,
        39,
        36,
        34,
        33,
        30,
        25,
        30,
        26,
        28,
        27,
        27,
        28,
        25,
        29,
        30,
        30,
        28,
        22,
        22,
        29,
        29,
        29,
        26,
        23,
        30,
        31,
        28,
        28,
        23,
        22,
        22,
        16,
        10,
        11,
        13,
        15,
        15,
        14,
        12,
        11,
        12,
        9,
        16,
        16,
        20,
        20,
        20,
        24,
        26,
        16,
        18,
        18,
        18,
        18,
        29,
        23,
        23,
        39,
        38,
        35,
        39,
        40,
        37,
        42,
        37,
        39,
        37,
        46,
        46,
        43,
        49,
        49,
        41,
        43,
        35,
        35,
        35,
        43,
        47,
        47,
        47,
        47,
        43,
        37,
        48,
        48,
        43,
        51,
        41,
        37,
        38,
        47,
        47,
        32,
        33,
        33,
        37,
        37,
        38,
        38,
        37,
        38,
        48,
        48,
        30,
        42,
        30,
        42,
        46,
        44,
        44,
        41,
        39,
        39,
        42,
        42,
        42,
        42,
        41,
        47,
        46,
        46,
        41,
        35,
        36,
        36,
        37,
        31,
        31,
        39,
        37,
        37,
        38,
        40,
        29,
        29,
        28,
        25,
        34,
        28,
        29,
        24,
        26,
        26
      ],
      "step": 60
    },
    "timestamp": "2025-11-20T22:10:32.583Z"
  },
  "stats_7d": {
    "success": true,
    "data": {
      "from": "2025-11-13T23:00:00.000Z",
      "to": "2025-11-20T22:09:00.000Z",
      "stats": [
        51,
        54,
        91,
        126,
        89,
        60,
        77,
        91,
        92,
        81,
        60,
        59,
        28,
        23,
        26,
        23,
        11,
        5,
        3,
        5,
        4,
        1,
        6,
        5,
        7,
        7,
        8,
        8,
        11,
        10,
        9,
        3,
        6,
        5,
        13,
        16,
        20,
        22,
        11,
        13,
        18,
        27,
        29,
        40,
        48,
        27,
        29,
        27,
        24,
        27,
        23,
        27,
        21,
        23,
        30,
        36,
        22,
        21,
        24,
        26,
        25,
        15,
        9,
        6,
        8,
        3,
        7,
        14,
        9,
        7,
        7,
        4,
        6,
        9,
        6,
        14,
        7,
        10,
        11,
        9,
        14,
        3,
        13,
        14,
        14,
        13,
        19,
        15,
        110,
        801,
        833,
        991,
        1313,
        1259,
        1238,
        1137,
        301,
        133,
        80,
        62,
        73,
        99,
        85,
        66,
        60,
        75,
        65,
        63,
        63,
        63,
        44,
        35,
        48,
        35,
        34,
        32,
        46,
        31,
        44,
        44,
        52,
        42,
        37,
        44,
        33,
        39,
        64,
        65,
        78,
        65,
        81,
        93,
        94,
        92,
        99,
        98,
        105,
        95,
        92,
        95,
        107,
        108,
        57,
        67,
        59,
        59,
        76,
        83,
        86,
        62,
        82,
        66,
        66,
        36,
        22,
        11,
        21,
        16,
        15,
        2,
        0,
        7,
        8,
        1,
        3,
        8,
        15,
        25,
        5,
        4,
        4,
        4,
        4,
        6,
        9,
        9,
        5,
        6,
        23,
        15,
        24,
        18,
        15,
        15,
        28,
        35,
        38,
        38,
        27,
        30,
        33,
        15,
        27,
        30,
        13,
        19,
        33,
        30,
        33,
        30,
        33,
        25,
        24,
        15,
        14,
        16,
        8,
        5,
        1,
        2,
        6,
        4,
        1,
        4,
        3,
        4,
        1,
        1,
        6,
        4,
        3,
        2,
        6,
        5,
        9,
        22,
        22,
        17,
        6,
        10,
        14,
        18,
        21,
        24,
        32,
        35,
        14,
        9,
        16,
        16,
        11,
        12,
        19,
        8,
        30,
        25,
        21,
        17,
        16,
        14,
        10,
        7,
        6,
        14,
        18,
        20,
        4,
        2,
        1,
        0,
        0,
        0,
        0,
        0,
        0,
        0,
        1,
        3,
        2,
        3,
        5,
        3,
        3,
        9,
        2,
        4,
        8,
        8,
        10,
        13,
        15,
        7,
        5,
        11,
        14,
        11,
        5,
        7,
        17,
        16,
        13,
        14,
        40,
        32,
        26,
        19,
        209,
        275,
        191,
        260,
        227,
        49,
        22,
        13,
        15,
        12,
        11,
        9,
        4,
        5,
        5,
        4,
        5,
        7,
        11,
        5,
        10,
        15,
        7,
        8,
        13,
        35,
        42,
        59,
        51,
        36,
        37,
        34,
        20,
        40,
        31,
        49,
        51,
        47,
        34
      ],
      "average_stats": [
        44,
        37,
        67,
        108,
        72,
        48,
        68,
        72,
        80,
        53,
        43,
        35,
        22,
        15,
        19,
        10,
        6,
        1,
        1,
        2,
        2,
        0,
        3,
        2,
        2,
        2,
        5,
        5,
        7,
        4,
        4,
        2,
        2,
        1,
        6,
        11,
        11,
        10,
        8,
        8,
        9,
        21,
        23,
        30,
        32,
        19,
        20,
        20,
        15,
        22,
        15,
        14,
        16,
        14,
        17,
        27,
        17,
        16,
        16,
        12,
        16,
        8,
        4,
        3,
        4,
        1,
        3,
        5,
        5,
        5,
        3,
        1,
        3,
        4,
        2,
        8,
        1,
        7,
        6,
        5,
        7,
        1,
        7,
        9,
        8,
        8,
        12,
        6,
        11,
        513,
        723,
        821,
        1130,
        1162,
        1168,
        652,
        196,
        99,
        64,
        48,
        63,
        85,
        67,
        48,
        47,
        54,
        45,
        54,
        48,
        47,
        31,
        25,
        38,
        25,
        28,
        26,
        29,
        22,
        31,
        37,
        45,
        32,
        27,
        31,
        22,
        29,
        56,
        52,
        63,
        49,
        55,
        73,
        74,
        80,
        79,
        66,
        88,
        81,
        83,
        82,
        90,
        71,
        45,
        52,
        36,
        39,
        52,
        64,
        70,
        45,
        54,
        49,
        40,
        24,
        14,
        6,
        11,
        9,
        7,
        0,
        0,
        2,
        4,
        0,
        1,
        3,
        7,
        16,
        2,
        1,
        2,
        2,
        2,
        4,
        4,
        5,
        3,
        3,
        10,
        5,
        19,
        12,
        11,
        9,
        20,
        22,
        30,
        23,
        18,
        15,
        21,
        11,
        17,
        24,
        9,
        13,
        22,
        23,
        25,
        23,
        25,
        18,
        14,
        7,
        9,
        8,
        3,
        2,
        0,
        0,
        3,
        2,
        0,
        1,
        1,
        1,
        0,
        0,
        2,
        2,
        1,
        0,
        3,
        3,
        4,
        10,
        10,
        9,
        2,
        7,
        4,
        11,
        13,
        16,
        18,
        17,
        8,
        5,
        9,
        6,
        5,
        9,
        8,
        6,
        21,
        20,
        13,
        12,
        9,
        11,
        6,
        3,
        2,
        8,
        13,
        13,
        2,
        1,
        0,
        0,
        0,
        0,
        0,
        0,
        0,
        0,
        0,
        1,
        0,
        0,
        2,
        2,
        0,
        5,
        1,
        2,
        3,
        4,
        6,
        8,
        11,
        4,
        3,
        7,
        9,
        7,
        2,
        3,
        12,
        10,
        7,
        10,
        22,
        21,
        19,
        12,
        65,
        182,
        143,
        157,
        116,
        30,
        10,
        9,
        10,
        6,
        6,
        4,
        1,
        2,
        2,
        2,
        2,
        3,
        5,
        2,
        4,
        8,
        4,
        5,
        6,
        24,
        29,
        42,
        32,
        24,
        25,
        18,
        14,
        28,
        21,
        32,
        41,
        39,
        28
      ],
      "step": 1800
    },
    "timestamp": "2025-11-20T22:10:34.052Z"
  },
  "fetched_at": "2025-11-20T22:10:34.010789Z"
}