{
  "map_code": "9950-7587-7979",
  "map_data": {
    "attributions": [],
    "ccu_record": 725,
    "ccu_record_date": "2025-10-19T16:30:00.000Z",
    "created": "2025-11-10T23:35:57.111Z",
    "discovery_intent": "PUBLIC",
    "id": "9950-7587-7979",
    "image_url": "https://cdn-0001.qstv.on.epicgames.com/pLOGTtUeLTyCMXqatZ/image/landscape_comp_b.jpeg",
    "image_url_cohort_b": null,
    "introduction": "Find the keys\nEnable all generators\nEscape",
    "lastSyncCcu": 175,
    "lastSyncDate": "2025-11-20T23:17:00.000Z",
    "lastSyncDisabled": false,
    "lobby_background_image_url": "https://cdn-0001.qstv.on.epicgames.com/hJLtiJbEpcOgxQCVVX/image/lobby.jpeg",
    "locale": "en",
    "max_players": 4,
    "metrics_day_id": 454,
    "metrics_minute_id": 476,
    "metrics_updated_date": "2025-11-20T18:33:50.928Z",
    "minutes_played": 10282416,
    "minutes_played_sync_date": "2025-11-18T19:38:20.432Z",
    "moderation_status": "Approved",
    "name": "The Playrooms",
    "owner_code": "pjlm",
    "owner_name": "Zo3niX",
    "published": "2025-08-02T13:41:00.440Z",
    "ratings": [
      "ACB_AGE_M",
      "PEGI_AGE_12",
      "GEN_AGE_12",
      "CLASSIND_AGE_12",
      "USK_AGE_12",
      "GRAC_AGE_ALL",
      "ESRB_AGE_T",
      "RUSSIA_AGE_12"
    ],
    "square_image_url": null,
    "state": "in_discovery",
    "tagline": "The Playrooms is a psychological experience where you'll need to find keys to access 4 differents generators spread across the biggest backroom maze made in fortnite but this time, you're not alone.\n\n\ud83d\udccc Made In UEFN (Creavtive 2.0)\n\ud83c\udf99\ufe0f Proximity Chat\n\ud83c\udfaf New Physic Update\n\ud83d\udcf9 First Person Camera\n\ud83d\udc65 Up To 4 Players Or Solo\n\ud83d\udc7a Gnome Invasion Event\n\u2753Lots Of Easter Eggs/Secrets\n\nHave Fun \ud83d\ude09",
    "tags": [
      "artistic",
      "co-op",
      "exploration",
      "horror"
    ],
    "type": "uefn",
    "version": 17,
    "video_id": "xnfjbiyiRpQLCQiBHm",
    "xp_enabled": true,
    "creator": {
      "id": "pjlm",
      "last_sync_ccu": 175,
      "last_sync_minutes_played": 10531818,
      "last_sync_minutes_played_position": 1944,
      "last_sync_position": 264,
      "lookup_avatar": "https://cdn-0001.qstv.on.epicgames.com/06PjkFEkdITy03PSDA2klG/image.jpg",
      "lookup_banner": "https://cdn2.unrealengine.com/t-ui-creatorprofile-banner-fallbackerror-1920x1080-3f830cc95018.png",
      "lookup_bio": null,
      "lookup_display_name": "pjlm",
      "lookup_follower_count": 2847,
      "lookup_socials_youtube": "https://youtube.com/@zo3nix?si=FoXp1iTQwHgFUT4z",
      "name": "Zo3niX"
    }
  },
  "stats_24h": {
    "success": true,
    "data": {
      "from": "2025-11-20T00:05:00.000Z",
      "to": "2025-11-21T00:02:00.000Z",
      "stats": [
        40,
        40,
        37,
        38,
        38,
        39,
        38,
        42,
        44,
        43,
        40,
        40,
        51,
        51,
        47,
        40,
        40,
        40,
        40,
        41,
        35,
        35,
        36,
        36,
        39,
        43,
        43,
        43,
        53,
        50,
        50,
        50,
        57,
        51,
        54,
        58,
        58,
        58,
        64,
        78,
        70,
        92,
        92,
        106,
        139,
        148,
        148,
        148,
        149,
        149,
        159,
        169,
        164,
        177,
        179,
        178,
        178,
        178,
        183,
        188,
        207,
        207,
        197,
        199,
        204,
        223,
        223,
        228,
        234,
        227,
        227,
        223,
        226,
        220,
        220,
        236,
        236,
        238,
        228,
        245,
        243,
        244,
        244,
        238,
        238,
        239,
        244,
        239,
        240,
        252,
        246,
        246,
        251,
        251,
        236,
        215,
        226,
        215,
        211,
        228,
        226,
        237,
        233,
        245,
        225,
        237,
        237,
        214,
        218,
        218,
        215,
        227,
        227,
        228,
        242,
        248,
        253,
        263,
        261,
        261,
        248,
        248,
        253,
        242,
        235,
        243,
        241,
        241,
        241,
        225,
        207,
        175,
        162,
        142,
        136,
        184,
        157,
        199,
        209,
        209,
        221,
        236,
        261,
        269,
        260,
        252,
        255,
        265,
        265,
        255,
        257,
        265,
        250,
        249,
        242,
        248,
        250,
        222,
        218,
        218,
        213,
        229,
        223,
        223,
        220,
        219,
        219,
        234,
        227,
        238,
        245,
        234,
        236,
        243,
        223,
        226,
        226,
        225,
        235,
        228,
        208,
        204,
        205,
        208,
        208,
        197,
        210,
        199,
        198,
        208,
        204,
        201,
        208,
        189,
        189,
        187,
        187,
        187,
        190,
        203,
        203,
        177,
        190,
        195,
        198,
        191,
        210,
        211,
        218,
        219,
        214,
        197,
        200,
        195,
        187,
        193,
        193,
        180,
        188,
        192,
        186,
        182,
        182,
        190,
        188,
        194,
        194,
        191,
        184,
        184,
        167,
        166,
        165,
        170,
        171,
        153,
        153,
        153,
        148,
        164,
        169,
        169,
        160,
        163,
        158,
        161,
        163,
        173,
        176,
        178,
        172,
        175,
        182,
        183,
        187,
        182,
        182,
        182,
        187,
        188,
        182,
        185,
        185,
        163,
        155,
        152,
        153,
        137,
        130,
        137,
        142,
        128,
        131,
        135,
        127,
        136,
        136,
        123,
        125,
        119,
        116,
        107,
        115,
        113,
        112,
        114,
        114,
        116,
        120,
        126,
        136,
        132,
        134,
        131,
        127,
        118,
        118,
        113,
        114,
        116,
        111,
        123,
        123,
        134,
        127,
        119,
        119,
        124,
        127,
        126,
        120,
        120,
        130,
        129,
        125,
        115,
        115,
        120,
        124,
        110,
        99,
        100,
        101,
        112,
        103,
        97,
        97,
        97,
        101,
        101,
        105,
        115,
        113,
        113,
        113,
        99,
        103,
        99,
        104,
        103,
        107,
        102,
        102,
        106,
        104,
        104,
        104,
        104,
        98,
        96,
        93,
        94,
        85,
        85,
        87,
        80,
        80,
        80,
        84,
        88,
        88,
        81,
        79,
        82,
        90,
        98,
        91,
        98,
        98,
        104,
        109,
        92,
        105,
        109,
        109,
        104,
        107,
        110,
        110,
        109,
        115,
        115,
        102,
        107,
        107,
        90,
        90,
        99,
        101,
        94,
        94,
        92,
        98,
        93,
        93,
        93,
        95,
        93,
        96,
        87,
        87,
        89,
        106,
        108,
        106,
        102,
        113,
        98,
        98,
        100,
        100,
        92,
        86,
        87,
        82,
        83,
        83,
        75,
        67,
        66,
        63,
        60,
        52,
        52,
        52,
        58,
        58,
        52,
        52,
        54,
        62,
        62,
        64,
        72,
        81,
        73,
        74,
        70,
        67,
        66,
        69,
        69,
        66,
        67,
        68,
        77,
        73,
        73,
        90,
        84,
        86,
        85,
        96,
        99,
        99,
        100,
        101,
        102,
        111,
        111,
        111,
        108,
        108,
        101,
        101,
        104,
        104,
        104,
        93,
        93,
        97,
        97,
        106,
        99,
        99,
        94,
        93,
        91,
        103,
        104,
        102,
        102,
        92,
        92,
        101,
        107,
        107,
        109,
        96,
        94,
        91,
        91,
        87,
        87,
        87,
        97,
        97,
        98,
        97,
        99,
        99,
        98,
        96,
        96,
        87,
        84,
        87,
        84,
        85,
        89,
        94,
        88,
        99,
        107,
        107,
        106,
        106,
        97,
        97,
        105,
        104,
        102,
        102,
        97,
        87,
        86,
        75,
        75,
        86,
        79,
        79,
        80,
        76,
        81,
        80,
        80,
        80,
        76,
        84,
        85,
        85,
        77,
        84,
        90,
        76,
        81,
        78,
        89,
        99,
        99,
        107,
        107,
        107,
        101,
        97,
        83,
        83,
        83,
        82,
        82,
        76,
        78,
        78,
        56,
        60,
        64,
        64,
        63,
        63,
        72,
        77,
        77,
        71,
        68,
        68,
        78,
        78,
        75,
        75,
        80,
        81,
        81,
        71,
        70,
        70,
        68,
        68,
        76,
        76,
        67,
        64,
        66,
        66,
        66,
        73,
        81,
        81,
        81,
        88,
        80,
        73,
        69,
        69,
        73,
        69,
        73,
        82,
        78,
        78,
        77,
        87,
        87,
        80,
        77,
        77,
        75,
        75,
        79,
        81,
        79,
        84,
        80,
        77,
        80,
        78,
        77,
        77,
        79,
        83,
        76,
        75,
        71,
        76,
        71,
        71,
        67,
        67,
        73,
        72,
        72,
        73,
        68,
        76,
        65,
        64,
        74,
        74,
        80,
        87,
        87,
        90,
        84,
        84,
        72,
        64,
        67,
        67,
        76,
        67,
        69,
        69,
        72,
        79,
        76,
        77,
        82,
        82,
        82,
        72,
        72,
        73,
        69,
        78,
        79,
        79,
        76,
        65,
        71,
        71,
        79,
        79,
        80,
        80,
        78,
        74,
        77,
        77,
        74,
        78,
        74,
        70,
        70,
        72,
        72,
        74,
        68,
        68,
        68,
        65,
        65,
        81,
        83,
        93,
        93,
        91,
        93,
        93,
        91,
        87,
        90,
        90,
        106,
        102,
        89,
        97,
        90,
        90,
        82,
        81,
        86,
        87,
        81,
        84,
        88,
        83,
        80,
        80,
        87,
        81,
        87,
        70,
        72,
        67,
        67,
        63,
        67,
        67,
        63,
        58,
        63,
        61,
        58,
        55,
        45,
        54,
        63,
        63,
        65,
        62,
        70,
        70,
        61,
        61,
        67,
        67,
        69,
        69,
        78,
        86,
        84,
        80,
        81,
        82,
        90,
        90,
        93,
        92,
        88,
        97,
        100,
        97,
        96,
        106,
        105,
        109,
        117,
        117,
        121,
        121,
        108,
        107,
        107,
        113,
        117,
        109,
        122,
        122,
        122,
        125,
        140,
        122,
        122,
        109,
        127,
        127,
        107,
        116,
        106,
        100,
        96,
        99,
        105,
        95,
        96,
        97,
        108,
        108,
        102,
        106,
        105,
        105,
        104,
        102,
        98,
        97,
        98,
        100,
        100,
        98,
        110,
        102,
        91,
        98,
        98,
        102,
        100,
        94,
        94,
        94,
        97,
        95,
        106,
        106,
        84,
        91,
        92,
        92,
        94,
        90,
        89,
        89,
        85,
        87,
        86,
        89,
        109,
        109,
        109,
        115,
        111,
        107,
        107,
        100,
        107,
        107,
        123,
        123,
        121,
        111,
        111,
        134,
        120,
        120,
        118,
        116,
        122,
        122,
        122,
        114,
        117,
        117,
        125,
        128,
        123,
        123,
        141,
        141,
        117,
        126,
        121,
        124,
        124,
        125,
        125,
        115,
        126,
        123,
        123,
        128,
        130,
        129,
        129,
        131,
        136,
        126,
        97,
        97,
        100,
        109,
        118,
        118,
        112,
        107,
        115,
        115,
        122,
        118,
        122,
        123,
        117,
        119,
        115,
        111,
        109,
        118,
        121,
        120,
        118,
        116,
        116,
        113,
        122,
        120,
        123,
        130,
        116,
        130,
        117,
        118,
        108,
        111,
        111,
        94,
        98,
        98,
        100,
        100,
        100,
        99,
        102,
        102,
        97,
        101,
        101,
        97,
        86,
        96,
        117,
        118,
        125,
        141,
        141,
        151,
        149,
        152,
        140,
        140,
        133,
        128,
        130,
        130,
        137,
        137,
        136,
        128,
        127,
        127,
        127,
        122,
        125,
        126,
        126,
        122,
        127,
        127,
        128,
        124,
        126,
        126,
        113,
        112,
        120,
        127,
        128,
        127,
        141,
        141,
        142,
        137,
        131,
        129,
        123,
        123,
        125,
        125,
        122,
        122,
        127,
        143,
        143,
        149,
        155,
        137,
        137,
        150,
        148,
        141,
        162,
        159,
        147,
        152,
        150,
        152,
        152,
        152,
        145,
        151,
        143,
        138,
        134,
        135,
        126,
        114,
        115,
        111,
        118,
        113,
        124,
        125,
        116,
        111,
        118,
        118,
        124,
        129,
        132,
        120,
        132,
        131,
        131,
        141,
        122,
        122,
        118,
        123,
        108,
        108,
        112,
        112,
        101,
        111,
        115,
        122,
        115,
        123,
        121,
        121,
        114,
        123,
        121,
        124,
        125,
        127,
        126,
        142,
        142,
        142,
        156,
        159,
        148,
        140,
        139,
        134,
        140,
        136,
        116,
        116,
        116,
        121,
        134,
        134,
        130,
        128,
        130,
        136,
        141,
        140,
        146,
        146,
        146,
        138,
        133,
        130,
        130,
        129,
        132,
        132,
        145,
        135,
        138,
        141,
        141,
        146,
        149,
        148,
        139,
        129,
        129,
        127,
        127,
        130,
        133,
        135,
        129,
        124,
        125,
        125,
        129,
        129,
        115,
        117,
        116,
        116,
        115,
        137,
        135,
        135,
        127,
        119,
        120,
        116,
        113,
        113,
        129,
        129,
        117,
        117,
        121,
        120,
        120,
        112,
        112,
        109,
        109,
        109,
        118,
        118,
        123,
        123,
        123,
        118,
        117,
        119,
        119,
        113,
        120,
        111,
        102,
        106,
        106,
        107,
        120,
        131,
        112,
        112,
        143,
        143,
        145,
        129,
        129,
        132,
        138,
        135,
        129,
        133,
        128,
        128,
        133,
        120,
        125,
        125,
        133,
        133,
        128,
        142,
        136,
        136,
        138,
        131,
        135,
        132,
        112,
        112,
        115,
        127,
        148,
        130,
        144,
        143,
        143,
        142,
        153,
        147,
        139,
        129,
        119,
        119,
        119,
        101,
        95,
        95,
        92,
        92,
        97,
        94,
        92,
        90,
        92,
        95,
        98,
        89,
        89,
        92,
        87,
        94,
        128,
        128,
        128,
        147,
        153,
        153,
        165,
        164,
        147,
        147,
        164,
        164,
        158,
        169,
        168,
        158,
        156,
        155,
        135,
        139,
        149,
        148,
        149,
        143,
        144,
        144,
        141,
        138,
        135,
        135,
        128,
        128,
        135,
        135,
        124,
        130,
        120,
        130,
        130,
        134,
        151,
        149,
        151,
        136,
        136,
        131,
        131,
        128,
        109,
        102,
        118,
        118,
        115,
        122,
        116,
        127,
        129,
        129,
        126,
        133,
        148,
        147,
        148,
        170,
        164,
        165,
        165,
        164,
        176,
        190,
        202,
        202,
        194,
        195,
        197,
        188,
        190,
        190,
        189,
        184,
        189,
        189,
        188,
        174,
        174,
        169,
        180,
        180,
        174,
        168,
        175,
        169,
        175,
        159,
        164,
        176,
        176,
        175,
        169,
        169,
        176,
        176,
        176,
        170,
        183,
        176,
        175,
        173,
        185,
        185,
        158,
        158,
        161,
        173,
        173,
        166,
        166,
        175,
        171,
        165,
        160,
        160,
        175,
        175,
        168,
        168,
        158,
        161,
        174,
        174,
        179,
        186,
        186,
        192,
        185,
        170,
        177,
        182,
        184,
        184,
        203,
        199,
        216,
        209,
        208,
        206,
        206,
        213,
        212,
        212,
        207,
        207,
        207,
        225,
        225,
        210,
        216,
        214,
        214,
        213,
        191,
        201,
        201,
        191,
        185,
        185,
        188,
        175,
        177,
        174,
        179,
        179,
        177,
        177,
        169,
        190,
        188,
        202,
        207,
        209,
        213,
        209,
        209,
        205,
        214,
        214,
        223,
        221,
        218,
        220,
        207,
        207,
        210,
        210,
        194,
        187,
        187,
        194,
        196,
        196,
        202,
        204,
        198,
        198,
        209,
        209,
        199,
        193,
        199,
        199,
        0,
        175,
        175
      ],
      "step": 60
    },
    "timestamp": "2025-11-21T00:04:01.145Z"
  },
  "stats_7d": {
    "success": true,
    "data": {
      "from": "2025-11-14T01:00:00.000Z",
      "to": "2025-11-21T00:02:00.000Z",
      "stats": [
        288,
        121,
        78,
        217,
        228,
        243,
        216,
        182,
        133,
        189,
        185,
        184,
        162,
        155,
        160,
        153,
        121,
        142,
        126,
        128,
        137,
        152,
        186,
        211,
        211,
        231,
        237,
        225,
        271,
        286,
        287,
        314,
        348,
        362,
        369,
        287,
        352,
        343,
        391,
        361,
        387,
        454,
        422,
        408,
        398,
        417,
        368,
        411,
        402,
        119,
        82,
        66,
        245,
        395,
        437,
        342,
        353,
        343,
        296,
        262,
        264,
        192,
        251,
        245,
        278,
        291,
        273,
        323,
        344,
        369,
        340,
        301,
        401,
        409,
        438,
        472,
        519,
        475,
        379,
        126,
        359,
        426,
        422,
        357,
        490,
        487,
        444,
        181,
        467,
        603,
        585,
        382,
        130,
        84,
        155,
        438,
        479,
        281,
        321,
        343,
        384,
        370,
        380,
        341,
        360,
        316,
        315,
        354,
        297,
        177,
        220,
        217,
        245,
        224,
        228,
        234,
        260,
        316,
        317,
        324,
        341,
        367,
        328,
        354,
        376,
        264,
        382,
        462,
        378,
        467,
        523,
        396,
        197,
        548,
        642,
        603,
        521,
        483,
        333,
        157,
        244,
        321,
        361,
        331,
        112,
        87,
        76,
        51,
        38,
        34,
        39,
        36,
        44,
        37,
        76,
        95,
        79,
        97,
        99,
        62,
        67,
        60,
        80,
        84,
        78,
        91,
        101,
        125,
        125,
        144,
        125,
        157,
        164,
        173,
        247,
        251,
        241,
        179,
        63,
        96,
        260,
        270,
        92,
        48,
        60,
        57,
        193,
        245,
        261,
        243,
        205,
        219,
        168,
        281,
        320,
        312,
        322,
        304,
        270,
        233,
        240,
        182,
        171,
        168,
        117,
        125,
        131,
        122,
        111,
        107,
        91,
        86,
        88,
        129,
        121,
        127,
        149,
        128,
        175,
        187,
        184,
        216,
        230,
        268,
        277,
        296,
        293,
        295,
        283,
        290,
        285,
        271,
        233,
        248,
        236,
        193,
        264,
        302,
        267,
        120,
        55,
        52,
        57,
        37,
        42,
        34,
        33,
        31,
        29,
        33,
        33,
        26,
        27,
        21,
        15,
        18,
        6,
        2,
        2,
        2,
        4,
        8,
        18,
        22,
        105,
        128,
        141,
        127,
        148,
        159,
        145,
        143,
        141,
        105,
        152,
        171,
        131,
        44,
        30,
        25,
        21,
        92,
        137,
        193,
        221,
        57,
        51,
        179,
        245,
        252,
        269,
        265,
        235,
        219,
        188,
        153,
        134,
        115,
        115,
        113,
        83,
        111,
        109,
        107,
        107,
        81,
        88,
        90,
        82,
        106,
        90,
        109,
        140,
        110,
        134,
        141,
        130,
        152,
        140,
        162,
        151,
        159,
        149,
        139,
        131,
        145,
        153,
        169,
        151,
        202,
        185,
        216,
        225,
        223,
        175
      ],
      "average_stats": [
        223,
        74,
        48,
        171,
        208,
        219,
        174,
        144,
        102,
        158,
        164,
        165,
        141,
        127,
        139,
        117,
        102,
        115,
        106,
        110,
        118,
        123,
        159,
        191,
        190,
        201,
        205,
        206,
        208,
        269,
        271,
        287,
        320,
        317,
        310,
        226,
        313,
        322,
        345,
        331,
        360,
        403,
        392,
        358,
        358,
        298,
        221,
        345,
        269,
        77,
        70,
        50,
        126,
        344,
        389,
        328,
        308,
        286,
        252,
        226,
        235,
        167,
        218,
        221,
        246,
        270,
        260,
        290,
        306,
        328,
        293,
        278,
        314,
        378,
        415,
        416,
        471,
        447,
        232,
        109,
        187,
        391,
        327,
        214,
        416,
        434,
        297,
        138,
        369,
        549,
        526,
        204,
        104,
        75,
        68,
        351,
        339,
        190,
        247,
        216,
        344,
        348,
        331,
        309,
        325,
        285,
        281,
        303,
        221,
        117,
        195,
        190,
        214,
        203,
        199,
        215,
        169,
        272,
        290,
        293,
        295,
        323,
        281,
        326,
        343,
        146,
        318,
        348,
        244,
        440,
        471,
        238,
        134,
        384,
        596,
        531,
        497,
        414,
        202,
        116,
        144,
        271,
        315,
        241,
        79,
        72,
        60,
        37,
        33,
        29,
        31,
        30,
        35,
        27,
        55,
        76,
        62,
        87,
        73,
        47,
        58,
        50,
        64,
        70,
        70,
        77,
        90,
        100,
        97,
        126,
        105,
        121,
        138,
        142,
        211,
        221,
        216,
        106,
        45,
        52,
        210,
        186,
        65,
        37,
        50,
        41,
        148,
        214,
        230,
        179,
        134,
        162,
        122,
        230,
        296,
        269,
        292,
        273,
        250,
        218,
        197,
        161,
        157,
        134,
        103,
        113,
        114,
        106,
        97,
        79,
        74,
        73,
        79,
        102,
        100,
        102,
        132,
        112,
        138,
        154,
        171,
        165,
        215,
        228,
        247,
        276,
        273,
        272,
        261,
        263,
        260,
        250,
        221,
        217,
        222,
        100,
        129,
        268,
        202,
        76,
        46,
        36,
        40,
        32,
        33,
        24,
        28,
        26,
        20,
        27,
        27,
        19,
        21,
        14,
        10,
        12,
        1,
        0,
        0,
        0,
        1,
        4,
        12,
        12,
        60,
        105,
        122,
        104,
        119,
        131,
        128,
        125,
        98,
        56,
        129,
        143,
        67,
        31,
        23,
        14,
        17,
        43,
        105,
        149,
        141,
        45,
        41,
        97,
        219,
        232,
        224,
        238,
        203,
        190,
        171,
        127,
        118,
        101,
        98,
        95,
        65,
        97,
        96,
        91,
        85,
        71,
        78,
        75,
        75,
        82,
        73,
        81,
        113,
        100,
        106,
        125,
        115,
        113,
        128,
        141,
        126,
        127,
        135,
        125,
        115,
        131,
        112,
        148,
        128,
        178,
        172,
        186,
        196,
        205,
        175
      ],
      "step": 1800
    },
    "timestamp": "2025-11-21T00:04:04.671Z"
  },
  "fetched_at": "2025-11-21T00:04:04.736600Z"
}