{
  "map_code": "8740-5832-8150",
  "fetched_at": "2025-11-25T19:30:13.389966",
  "status": "success",
  "metrics": {
    "averageMinutesPerPlayer": [
      {
        "value": 30.47,
        "timestamp": "2025-11-19T00:00:00.000Z"
      },
      {
        "value": 32.04,
        "timestamp": "2025-11-20T00:00:00.000Z"
      },
      {
        "value": 32.35,
        "timestamp": "2025-11-21T00:00:00.000Z"
      },
      {
        "value": 31.71,
        "timestamp": "2025-11-22T00:00:00.000Z"
      },
      {
        "value": 30.97,
        "timestamp": "2025-11-23T00:00:00.000Z"
      },
      {
        "value": 31.02,
        "timestamp": "2025-11-24T00:00:00.000Z"
      },
      {
        "value": 28.92,
        "timestamp": "2025-11-25T00:00:00.000Z"
      }
    ],
    "peakCCU": [
      {
        "value": 153,
        "timestamp": "2025-11-19T00:00:00.000Z"
      },
      {
        "value": 174,
        "timestamp": "2025-11-20T00:00:00.000Z"
      },
      {
        "value": 373,
        "timestamp": "2025-11-21T00:00:00.000Z"
      },
      {
        "value": 325,
        "timestamp": "2025-11-22T00:00:00.000Z"
      },
      {
        "value": 595,
        "timestamp": "2025-11-23T00:00:00.000Z"
      },
      {
        "value": 303,
        "timestamp": "2025-11-24T00:00:00.000Z"
      },
      {
        "value": 294,
        "timestamp": "2025-11-25T00:00:00.000Z"
      }
    ],
    "favorites": [
      {
        "value": 72,
        "timestamp": "2025-11-19T00:00:00.000Z"
      },
      {
        "value": 111,
        "timestamp": "2025-11-20T00:00:00.000Z"
      },
      {
        "value": 245,
        "timestamp": "2025-11-21T00:00:00.000Z"
      },
      {
        "value": 235,
        "timestamp": "2025-11-22T00:00:00.000Z"
      },
      {
        "value": 451,
        "timestamp": "2025-11-23T00:00:00.000Z"
      },
      {
        "value": 195,
        "timestamp": "2025-11-24T00:00:00.000Z"
      },
      {
        "value": 96,
        "timestamp": "2025-11-25T00:00:00.000Z"
      }
    ],
    "minutesPlayed": [
      {
        "value": 83610,
        "timestamp": "2025-11-19T00:00:00.000Z"
      },
      {
        "value": 117972,
        "timestamp": "2025-11-20T00:00:00.000Z"
      },
      {
        "value": 181861,
        "timestamp": "2025-11-21T00:00:00.000Z"
      },
      {
        "value": 174365,
        "timestamp": "2025-11-22T00:00:00.000Z"
      },
      {
        "value": 295885,
        "timestamp": "2025-11-23T00:00:00.000Z"
      },
      {
        "value": 169601,
        "timestamp": "2025-11-24T00:00:00.000Z"
      },
      {
        "value": 101520,
        "timestamp": "2025-11-25T00:00:00.000Z"
      }
    ],
    "recommendations": [
      {
        "value": 2,
        "timestamp": "2025-11-19T00:00:00.000Z"
      },
      {
        "value": 2,
        "timestamp": "2025-11-20T00:00:00.000Z"
      },
      {
        "value": 7,
        "timestamp": "2025-11-21T00:00:00.000Z"
      },
      {
        "value": 9,
        "timestamp": "2025-11-22T00:00:00.000Z"
      },
      {
        "value": 13,
        "timestamp": "2025-11-23T00:00:00.000Z"
      },
      {
        "value": 10,
        "timestamp": "2025-11-24T00:00:00.000Z"
      },
      {
        "value": 5,
        "timestamp": "2025-11-25T00:00:00.000Z"
      }
    ],
    "plays": [
      {
        "value": 3663,
        "timestamp": "2025-11-19T00:00:00.000Z"
      },
      {
        "value": 5292,
        "timestamp": "2025-11-20T00:00:00.000Z"
      },
      {
        "value": 8762,
        "timestamp": "2025-11-21T00:00:00.000Z"
      },
      {
        "value": 8179,
        "timestamp": "2025-11-22T00:00:00.000Z"
      },
      {
        "value": 13455,
        "timestamp": "2025-11-23T00:00:00.000Z"
      },
      {
        "value": 7581,
        "timestamp": "2025-11-24T00:00:00.000Z"
      },
      {
        "value": 4519,
        "timestamp": "2025-11-25T00:00:00.000Z"
      }
    ],
    "uniquePlayers": [
      {
        "value": 2744,
        "timestamp": "2025-11-19T00:00:00.000Z"
      },
      {
        "value": 3682,
        "timestamp": "2025-11-20T00:00:00.000Z"
      },
      {
        "value": 5622,
        "timestamp": "2025-11-21T00:00:00.000Z"
      },
      {
        "value": 5499,
        "timestamp": "2025-11-22T00:00:00.000Z"
      },
      {
        "value": 9554,
        "timestamp": "2025-11-23T00:00:00.000Z"
      },
      {
        "value": 5468,
        "timestamp": "2025-11-24T00:00:00.000Z"
      },
      {
        "value": 3512,
        "timestamp": "2025-11-25T00:00:00.000Z"
      }
    ],
    "retention": [
      {
        "d1": 0.31,
        "d7": 0.11,
        "timestamp": "2025-11-19T00:00:00.000Z"
      },
      {
        "d1": 0.3,
        "d7": 0.11,
        "timestamp": "2025-11-20T00:00:00.000Z"
      },
      {
        "d1": 0.35,
        "d7": 0.16,
        "timestamp": "2025-11-21T00:00:00.000Z"
      },
      {
        "d1": 0.33,
        "d7": 0.17,
        "timestamp": "2025-11-22T00:00:00.000Z"
      },
      {
        "d1": 0.29,
        "d7": 0.13,
        "timestamp": "2025-11-23T00:00:00.000Z"
      },
      {
        "d1": 0.31,
        "d7": 0.12,
        "timestamp": "2025-11-24T00:00:00.000Z"
      },
      {
        "d1": 0.19,
        "d7": 0.15,
        "timestamp": "2025-11-25T00:00:00.000Z"
      }
    ]
  }
}