{
  "map_code": "4838-6070-3736",
  "fetched_at": "2025-11-25T19:29:27.519810",
  "status": "success",
  "metrics": {
    "averageMinutesPerPlayer": [
      {
        "value": 15.77,
        "timestamp": "2025-11-19T00:00:00.000Z"
      },
      {
        "value": 16.34,
        "timestamp": "2025-11-20T00:00:00.000Z"
      },
      {
        "value": 16.51,
        "timestamp": "2025-11-21T00:00:00.000Z"
      },
      {
        "value": 16.03,
        "timestamp": "2025-11-22T00:00:00.000Z"
      },
      {
        "value": 16.47,
        "timestamp": "2025-11-23T00:00:00.000Z"
      },
      {
        "value": 16.82,
        "timestamp": "2025-11-24T00:00:00.000Z"
      },
      {
        "value": 15.9,
        "timestamp": "2025-11-25T00:00:00.000Z"
      }
    ],
    "peakCCU": [
      {
        "value": 218,
        "timestamp": "2025-11-19T00:00:00.000Z"
      },
      {
        "value": 251,
        "timestamp": "2025-11-20T00:00:00.000Z"
      },
      {
        "value": 110,
        "timestamp": "2025-11-21T00:00:00.000Z"
      },
      {
        "value": 297,
        "timestamp": "2025-11-22T00:00:00.000Z"
      },
      {
        "value": 332,
        "timestamp": "2025-11-23T00:00:00.000Z"
      },
      {
        "value": 185,
        "timestamp": "2025-11-24T00:00:00.000Z"
      },
      {
        "value": 105,
        "timestamp": "2025-11-25T00:00:00.000Z"
      }
    ],
    "favorites": [
      {
        "value": 797,
        "timestamp": "2025-11-19T00:00:00.000Z"
      },
      {
        "value": 480,
        "timestamp": "2025-11-20T00:00:00.000Z"
      },
      {
        "value": 295,
        "timestamp": "2025-11-21T00:00:00.000Z"
      },
      {
        "value": 686,
        "timestamp": "2025-11-22T00:00:00.000Z"
      },
      {
        "value": 1075,
        "timestamp": "2025-11-23T00:00:00.000Z"
      },
      {
        "value": 474,
        "timestamp": "2025-11-24T00:00:00.000Z"
      },
      {
        "value": 221,
        "timestamp": "2025-11-25T00:00:00.000Z"
      }
    ],
    "minutesPlayed": [
      {
        "value": 125791,
        "timestamp": "2025-11-19T00:00:00.000Z"
      },
      {
        "value": 86327,
        "timestamp": "2025-11-20T00:00:00.000Z"
      },
      {
        "value": 51931,
        "timestamp": "2025-11-21T00:00:00.000Z"
      },
      {
        "value": 132697,
        "timestamp": "2025-11-22T00:00:00.000Z"
      },
      {
        "value": 236162,
        "timestamp": "2025-11-23T00:00:00.000Z"
      },
      {
        "value": 109058,
        "timestamp": "2025-11-24T00:00:00.000Z"
      },
      {
        "value": 46690,
        "timestamp": "2025-11-25T00:00:00.000Z"
      }
    ],
    "recommendations": [
      {
        "value": 168,
        "timestamp": "2025-11-19T00:00:00.000Z"
      },
      {
        "value": 106,
        "timestamp": "2025-11-20T00:00:00.000Z"
      },
      {
        "value": 58,
        "timestamp": "2025-11-21T00:00:00.000Z"
      },
      {
        "value": 185,
        "timestamp": "2025-11-22T00:00:00.000Z"
      },
      {
        "value": 289,
        "timestamp": "2025-11-23T00:00:00.000Z"
      },
      {
        "value": 135,
        "timestamp": "2025-11-24T00:00:00.000Z"
      },
      {
        "value": 52,
        "timestamp": "2025-11-25T00:00:00.000Z"
      }
    ],
    "plays": [
      {
        "value": 8636,
        "timestamp": "2025-11-19T00:00:00.000Z"
      },
      {
        "value": 5852,
        "timestamp": "2025-11-20T00:00:00.000Z"
      },
      {
        "value": 3383,
        "timestamp": "2025-11-21T00:00:00.000Z"
      },
      {
        "value": 9036,
        "timestamp": "2025-11-22T00:00:00.000Z"
      },
      {
        "value": 15790,
        "timestamp": "2025-11-23T00:00:00.000Z"
      },
      {
        "value": 7134,
        "timestamp": "2025-11-24T00:00:00.000Z"
      },
      {
        "value": 3156,
        "timestamp": "2025-11-25T00:00:00.000Z"
      }
    ],
    "uniquePlayers": [
      {
        "value": 7979,
        "timestamp": "2025-11-19T00:00:00.000Z"
      },
      {
        "value": 5282,
        "timestamp": "2025-11-20T00:00:00.000Z"
      },
      {
        "value": 3145,
        "timestamp": "2025-11-21T00:00:00.000Z"
      },
      {
        "value": 8277,
        "timestamp": "2025-11-22T00:00:00.000Z"
      },
      {
        "value": 14340,
        "timestamp": "2025-11-23T00:00:00.000Z"
      },
      {
        "value": 6485,
        "timestamp": "2025-11-24T00:00:00.000Z"
      },
      {
        "value": 2936,
        "timestamp": "2025-11-25T00:00:00.000Z"
      }
    ],
    "retention": [
      {
        "d1": 0.03,
        "d7": 0,
        "timestamp": "2025-11-19T00:00:00.000Z"
      },
      {
        "d1": 0.03,
        "d7": 0,
        "timestamp": "2025-11-20T00:00:00.000Z"
      },
      {
        "d1": 0.03,
        "d7": 0,
        "timestamp": "2025-11-21T00:00:00.000Z"
      },
      {
        "d1": 0.02,
        "d7": 0,
        "timestamp": "2025-11-22T00:00:00.000Z"
      },
      {
        "d1": 0.03,
        "d7": 0,
        "timestamp": "2025-11-23T00:00:00.000Z"
      },
      {
        "d1": 0.04,
        "d7": 0.01,
        "timestamp": "2025-11-24T00:00:00.000Z"
      },
      {
        "d1": 0.03,
        "d7": 0,
        "timestamp": "2025-11-25T00:00:00.000Z"
      }
    ]
  }
}